README.rst
setup.py
metrique/__init__.py
metrique/_version.py
metrique/core_api.py
metrique/metrique.py
metrique/mongodb.py
metrique/parse.py
metrique/plotting.py
metrique/reporting.py
metrique/result.py
metrique/sqlalchemy.py
metrique/utils.py
metrique.egg-info/PKG-INFO
metrique.egg-info/SOURCES.txt
metrique.egg-info/dependency_links.txt
metrique.egg-info/not-zip-safe
metrique.egg-info/requires.txt
metrique.egg-info/top_level.txt
metrique/cubes/__init__.py
metrique/cubes/csvdata/__init__.py
metrique/cubes/csvdata/rows.py
metrique/cubes/gitdata/__init__.py
metrique/cubes/gitdata/commit.py
metrique/cubes/osinfo/__init__.py
metrique/cubes/osinfo/rpm.py
metrique/cubes/sqldata/__init__.py
metrique/cubes/sqldata/generic.py