Metadata-Version: 1.1
Name: metrique
Version: 0.3.1-2
Summary: Metrique - Client Libraries
Home-page: https://github.com/kejbaly2/metrique
Author: Chris Ward
Author-email: cward@redhat.com
License: GPLv3
Download-URL: https://github.com/kejbaly2/metrique/archive/master.zip
Keywords: data,mining,information,mongo,etl,analysis,search,query
Platform: UNKNOWN
Classifier: Development Status :: 4 - Beta
Classifier: Intended Audience :: Science/Research
Classifier: License :: OSI Approved :: GNU General Public License v3 (GPLv3)
Classifier: Natural Language :: English
Classifier: Programming Language :: Python :: 2.6
Classifier: Programming Language :: Python :: 2.7
Classifier: Programming Language :: Python :: 2 :: Only
Classifier: Topic :: Database
Classifier: Topic :: Office/Business
Classifier: Topic :: Scientific/Engineering
Classifier: Topic :: Scientific/Engineering :: Artificial Intelligence
Classifier: Topic :: Scientific/Engineering :: Visualization
Classifier: Topic :: Utilities
Requires: anyconfig
Requires: decorator
Requires: lockfile
Requires: python_dateutil
Requires: pytzsimplejson
Requires: sqlalchemy (>=0.9.4)
Requires: virtualenv (>=1.11)
Provides: metrique
